LICENSE.txt
README.md
pyproject.toml
setup.py
ojph/__init__.py
ojph/_imread.py
ojph/_imwrite.py
ojph/_static_version.py
ojph/_version.py
ojph/ojph_bindings.cpp
ojph.egg-info/PKG-INFO
ojph.egg-info/SOURCES.txt
ojph.egg-info/dependency_links.txt
ojph.egg-info/not-zip-safe
ojph.egg-info/requires.txt
ojph.egg-info/top_level.txt
tests/test_imread_failures.py
tests/test_imread_from_memory.py
tests/test_lossless_compression.py
tests/test_memory_compression.py
tests/test_package.py
tests/test_progression_order.py